smspva/__init__.py
smspva-0.0.1.dist-info/DESCRIPTION.rst
smspva-0.0.1.dist-info/METADATA
smspva-0.0.1.dist-info/RECORD
smspva-0.0.1.dist-info/WHEEL
smspva-0.0.1.dist-info/metadata.json
smspva-0.0.1.dist-info/top_level.txt
