Metadata-Version: 2.0
Name: smspva
Version: 0.0.1
Summary: An API wrapper for the website smspva
Home-page: https://github.com/pyCynical/smspva
Author: pyCynical
Author-email: enxfusion@gmail.com
License: GNU
Keywords: smspva,sms
Platform: UNKNOWN
Requires-Dist: requests
